gtimelog2tick.py
gtimelog2tick-0.2.2.dist-info/LICENSE
gtimelog2tick-0.2.2.dist-info/METADATA
gtimelog2tick-0.2.2.dist-info/WHEEL
gtimelog2tick-0.2.2.dist-info/entry_points.txt
gtimelog2tick-0.2.2.dist-info/top_level.txt
gtimelog2tick-0.2.2.dist-info/RECORD
