Metadata-Version: 2.1
Name: gtimelog2tick
Version: 0.2.2
Summary: Create entries in tickspot's tick from Gtimelog journal.
Home-page: https://github.com/minddistrict/gtimelog2tick
Author: Michael Howitz
Author-email: icemac@gmx.net
License: GPL
Keywords: gtimelog,tick,upload
Classifier: Development Status :: 4 - Beta
Classifier: License :: OSI Approved :: GNU General Public License (GPL)
Classifier: Programming Language :: Python :: 3.11
Classifier: Programming Language :: Python :: 3.12
Requires-Python: >= 3.11
License-File: LICENSE
Requires-Dist: requests
